Metadata-Version: 1.0
Name: NewLib2
Version: 1.2.3
Summary: My first Python library
Home-page: UNKNOWN
Author: Hamed
Author-email: UNKNOWN
License: UNKNOWN
Platform: UNKNOWN
